{
  "name": "dragonegg",
  "invisible": true,
  "slot": 0,
  "levels": [
    {
      "cooldown": 340,
      "duration": 40,
      "cost": 80,
      "material": "FEATHER",
      "displayName": "§cDragon egg",
      "lore": [],
      "amount": 1
    },
    {
      "cooldown": 340,
      "duration": 45,
      "cost": 100,
      "material": "FEATHER",
      "displayName": "§cDragon egg",
      "lore": [],
      "amount": 1
    },
    {
      "cooldown": 340,
      "duration": 50,
      "cost": 120,
      "material": "FEATHER",
      "displayName": "§cDragon egg",
      "lore": [],
      "amount": 1
    },
    {
      "cooldown": 340,
      "duration": 55,
      "cost": 140,
      "material": "FEATHER",
      "displayName": "§cDragon egg",
      "lore": [],
      "amount": 1
    },
    {
      "cooldown": 340,
      "duration": 60,
      "cost": 160,
      "material": "FEATHER",
      "displayName": "§cDragon egg",
      "lore": [],
      "amount": 1
    }
  ]
}
