{
  "name": "invisibilitypotion",
  "slot": 0,
  "levels": [
    {
      "cooldown": 400,
      "duration": 60,
      "material": "GLASS_BOTTLE",
      "displayName": "§cInvisibility Potion",
      "lore": [
        "§aСтаньте невидимым для окружающих",
        "§6Уровень 1"
      ],
      "amount": 1
    },
    {
      "cooldown": 400,
      "duration": 80,
      "material": "GLASS_BOTTLE",
      "displayName": "§cInvisibility Potion",
      "lore": [
        "§aСтаньте невидимым для окружающих",
        "§6Уровень 2"
      ],
      "amount": 1
    },
    {
      "cooldown": 400,
      "duration": 100,
      "material": "GLASS_BOTTLE",
      "displayName": "§cInvisibility Potion",
      "lore": [
        "§aСтаньте невидимым для окружающих",
        "§6Уровень 3"
      ],
      "amount": 1
    }
  ]
}